modelity/__init__.py
modelity/_internal/__init__.py
modelity/_internal/hooks.py
modelity/_internal/model.py
modelity/_internal/registry.py
modelity/_internal/type_descriptors/__init__.py
modelity/_internal/type_descriptors/all.py
modelity/_internal/type_descriptors/collections.py
modelity/_internal/type_descriptors/model.py
modelity/_internal/type_descriptors/simple.py
modelity/_internal/type_descriptors/special.py
modelity/_utils.py
modelity/api.py
modelity/constraints.py
modelity/error.py
modelity/exc.py
modelity/helpers.py
modelity/hooks.py
modelity/interface.py
modelity/loc.py
modelity/model.py
modelity/types.py
modelity/unset.py
modelity/visitors.py
modelity-0.27.0.dist-info/METADATA
modelity-0.27.0.dist-info/WHEEL
modelity-0.27.0.dist-info/licenses/LICENSE.txt
modelity-0.27.0.dist-info/RECORD
