Metadata-Version: 2.4
Name: modelity
Version: 0.27.0
Summary: Data parsing and validation library for Python
License: MIT
License-File: LICENSE.txt
Keywords: parsing,validation,modelling,parser,validator,model,library,toolkit
Author: Maciej Wiatrzyk
Author-email: maciej.wiatrzyk@gmail.com
Requires-Python: >=3.10,<4
Classifier: Development Status :: 4 - Beta
Classifier: Intended Audience :: Developers
Classifier: License :: OSI Approved :: MIT License
Classifier: Operating System :: OS Independent
Classifier: Programming Language :: Python :: 3
Classifier: Programming Language :: Python :: 3.10
Classifier: Programming Language :: Python :: 3.11
Classifier: Programming Language :: Python :: 3.12
Classifier: Programming Language :: Python :: 3.13
Classifier: Programming Language :: Python :: 3.14
Classifier: Topic :: Software Development :: Libraries
Requires-Dist: typing-extensions (>=4.12.2,<5.0.0)
Project-URL: Repository, https://github.com/mwiatrzyk/modelity
